dump1090exporter/__init__.py
dump1090exporter/__main__.py
dump1090exporter/exporter.py
dump1090exporter/metrics.py
dump1090exporter-22.3.0.dist-info/LICENSE
dump1090exporter-22.3.0.dist-info/METADATA
dump1090exporter-22.3.0.dist-info/WHEEL
dump1090exporter-22.3.0.dist-info/entry_points.txt
dump1090exporter-22.3.0.dist-info/top_level.txt
dump1090exporter-22.3.0.dist-info/RECORD
