Metadata-Version: 2.1
Name: dump1090exporter
Version: 22.3.0
Summary: A Prometheus metrics exporter for the dump1090 Mode S decoder for RTLSDR
Home-page: https://github.com/claws/dump1090-exporter
Author: Chris Laws
Author-email: clawsicus@gmail.com
License: MIT
Keywords: prometheus,monitoring,metrics,dump1090,ADSB
Platform: UNKNOWN
Classifier: Development Status :: 5 - Production/Stable
Classifier: Intended Audience :: Developers
Classifier: License :: OSI Approved :: MIT License
Classifier: Natural Language :: English
Classifier: Operating System :: OS Independent
Classifier: Programming Language :: Python :: 3.6
Classifier: Programming Language :: Python :: 3.7
Classifier: Programming Language :: Python :: 3.8
Classifier: Programming Language :: Python :: 3.9
Classifier: Programming Language :: Python :: 3.10
Classifier: Topic :: System :: Monitoring
Requires-Dist: aiohttp (==3.8.1)
Requires-Dist: aioprometheus[aiohttp] (==22.3.0)
Provides-Extra: develop
Requires-Dist: asynctest (==0.13.0) ; extra == 'develop'
Requires-Dist: black (==21.9b0) ; extra == 'develop'
Requires-Dist: coverage (==6.0) ; extra == 'develop'
Requires-Dist: isort (==5.9.3) ; extra == 'develop'
Requires-Dist: mypy (==0.910) ; extra == 'develop'
Requires-Dist: pylint (==2.11.1) ; extra == 'develop'
Requires-Dist: wheel (==0.37.0) ; extra == 'develop'
Provides-Extra: uvloop
Requires-Dist: uvloop (==0.16.0) ; extra == 'uvloop'
